{
  "('barrier',)": "none",
  "('barrier', 'release')": "none",
  "('barrier', 'evacuated', 'release')": "none",
  "('rain',)": "barrier",
  "('barrier', 'evacuated')": "none",
  "('barrier', 'collapse', 'crisis')": "evacuate",
  "('barrier', 'collapse', 'crisis', 'release')": "evacuate",
  "('rain', 'release')": "barrier",
  "('evacuated', 'flood', 'rain')": "barrier",
  "('barrier', 'evacuated', 'rain', 'release')": "none",
  "('flood',)": "barrier",
  "('damage', 'release')": "evacuate",
  "('barrier', 'collapse', 'release')": "evacuate",
  "('collapse', 'damage', 'flood', 'rain')": "evacuate",
  "('barrier', 'collapse', 'rain')": "evacuate",
  "('barrier', 'collapse')": "release",
  "('damage', 'evacuated', 'flood')": "barrier",
  "('damage', 'flood', 'rain')": "barrier",
  "('barrier', 'rain')": "none",
  "('damage', 'evacuated', 'flood', 'rain')": "barrier",
  "('release',)": "barrier",
  "('barrier', 'collapse', 'rain', 'release')": "barrier",
  "('damage', 'evacuated', 'release')": "barrier",
  "('flood', 'rain')": "barrier",
  "('damage', 'flood', 'release')": "barrier",
  "('collapse', 'damage', 'flood')": "evacuate",
  "('barrier', 'collapse', 'crisis', 'rain')": "evacuate",
  "('collapse', 'damage', 'flood', 'release')": "evacuate",
  "('barrier', 'collapse', 'crisis', 'rain', 'release')": "evacuate",
  "('evacuated', 'flood', 'rain', 'release')": "barrier",
  "('collapse', 'crisis', 'damage', 'flood', 'rain')": "evacuate",
  "('evacuated',)": "barrier",
  "('damage', 'rain', 'release')": "barrier",
  "('evacuated', 'rain')": "barrier",
  "('collapse', 'crisis', 'damage', 'flood', 'release')": "evacuate",
  "('collapse', 'damage', 'rain', 'release')": "evacuate",
  "('evacuated', 'rain', 'release')": "barrier",
  "('damage', 'evacuated', 'rain', 'release')": "barrier",
  "('damage', 'evacuated', 'flood', 'rain', 'release')": "barrier",
  "('evacuated', 'release')": "barrier",
  "('flood', 'release')": "barrier",
  "('flood', 'rain', 'release')": "barrier",
  "('evacuated', 'flood')": "barrier",
  "('damage', 'evacuated', 'flood', 'release')": "none",
  "('collapse', 'crisis', 'damage', 'flood')": "barrier"
}